pyeverlights/__init__.py
pyeverlights-0.1.0.dist-info/METADATA
pyeverlights-0.1.0.dist-info/RECORD
pyeverlights-0.1.0.dist-info/WHEEL
pyeverlights-0.1.0.dist-info/top_level.txt
